README.md
setup.py
Claver_Message_Board.egg-info/PKG-INFO
Claver_Message_Board.egg-info/SOURCES.txt
Claver_Message_Board.egg-info/dependency_links.txt
Claver_Message_Board.egg-info/top_level.txt
interface/__init__.py
interface/calendar/CalendarManager.py
interface/calendar/__init__.py
interface/doodle/DoodleManager.py
interface/doodle/__init__.py
interface/games/GamesManager.py
interface/games/__init__.py
interface/gui/CategoryManagerTemplate.py
interface/gui/ContentLayer.py
interface/gui/GuiManager.py
interface/gui/MenuLayer.py
interface/gui/NotificationLayer.py
interface/gui/__init__.py
interface/lists/ListsManager.py
interface/lists/__init__.py
interface/messages/MessagesManager.py
interface/messages/__init__.py
interface/news/NewsManager.py
interface/news/__init__.py
interface/photos/PhotosManager.py
interface/photos/__init__.py
interface/settings/Search.py
interface/settings/Settings.py
interface/settings/SettingsManager.py
interface/settings/SettingsMenu.py
interface/settings/SettingsMenuTemplate.py
interface/settings/__init__.py
interface/settings/categories/AboutMenu.py
interface/settings/categories/AccountMenu.py
interface/settings/categories/GeneralMenu.py
interface/settings/categories/NetworkMenu.py
interface/settings/categories/ThemeMenu.py
interface/settings/categories/__init__.py
interface/timer/TimerManager.py
interface/timer/__init__.py
interface/widgets/Clock.py
interface/widgets/ColourWheel.py
interface/widgets/Weather.py
interface/widgets/__init__.py