Metadata-Version: 2.1
Name: Claver-Message-Board
Version: 0.0.3
Summary: Interactive messaging board for RPi
Home-page: https://github.com/mccolm-robotics/Claver-Interactive-Message-Board
License: MIT
Platform: UNKNOWN
